{
  "marshall-monitor-iii-anc": {
    "best_price": 16720.0,
    "best_source": "Vakkorama Online Shop",
    "best_title": "Vakkorama Marshall Monitor Iii Anc Kulak Üstü Kulaklık",
    "best_link": "https://www.vakkorama.com.tr/kulaklik/monitor-iii-anc-kulak-ustu-kulaklik-p-M406022746-0002",
    "last_checked_at": "2026-06-05T15:58:22.680934+00:00",
    "top_5": [
      {
        "title": "Vakkorama Marshall Monitor Iii Anc Kulak Üstü Kulaklık",
        "source": "Vakkorama Online Shop",
        "price": 16720.0,
        "price_text": "₺16.720,00",
        "shipping": "Ücretsiz",
        "total": "₺16.720,00",
        "link": "https://www.vakkorama.com.tr/kulaklik/monitor-iii-anc-kulak-ustu-kulaklik-p-M406022746-0002",
        "rating": null,
        "reviews": null,
        "tag": null
      },
      {
        "title": "Marshall Monitor III ANC Aktif Gürültü Azaltma Bluetooth Kulaklık, 70 Saat Çalma Süresi - Siyah",
        "source": "Amazon.com.tr",
        "price": 19900.0,
        "price_text": "₺19.900,00",
        "shipping": "Ücretsiz",
        "total": "₺19.900,00",
        "link": "https://www.amazon.com.tr/Marshall-Monitor-G%C3%BCr%C3%BClt%C3%BC-Bluetooth-Kulakl%C4%B1k/dp/B0DFDT1TWC?source=ps-sl-shoppingads-lpcontext&ref_=fplfs&psc=1&smid=A1UNQM1SR2CHM",
        "rating": null,
        "reviews": null,
        "tag": null
      },
      {
        "title": "Marshall Monitor III ANC Kulakustu Bluetooth Kulaklik",
        "source": "Trendyol",
        "price": 19900.0,
        "price_text": "₺19.900,00",
        "shipping": "Ücretsiz",
        "total": "₺19.900,00",
        "link": "https://www.trendyol.com/marshall/monitor-iii-anc-kulakustu-bluetooth-kulaklik-p-874393723?boutiqueId=61&merchantId=624588&storefrontId=1&countryCode=TR&language=tr&gads=true",
        "rating": null,
        "reviews": null,
        "tag": null
      },
      {
        "title": "Marshall Monitor Iii Anc Kablosuz Bluetooth Kulaklik Siyah",
        "source": "Techno Plus Kıbrıs",
        "price": 19958.4,
        "price_text": "₺19.958,40",
        "shipping": null,
        "total": "₺19.958,40",
        "link": "https://technopluskibris.com/telefon/kulakliklar/kulak-ustu/prd-marshall-monitor-iii-anc-kablosuz-bluetooth-kulaklik-siyah",
        "rating": null,
        "reviews": null,
        "tag": null
      },
      {
        "title": "Marshall Monitor III ANC Kablosuz Kulak Üstü Kulaklık Siyah",
        "source": "MediaMarkt Türkiye",
        "price": 20899.0,
        "price_text": "₺20.899,00",
        "shipping": "Ücretsiz",
        "total": "₺20.899,00",
        "link": "https://www.mediamarkt.com.tr/tr/product/_marshall-monitor-iii-anc-kablosuz-kulak-ustu-kulaklik-siyah-1241543.html",
        "rating": 4.7,
        "reviews": 10305,
        "tag": null
      }
    ]
  }
}